packagr/.mypy_cache/3.7/@plugins_snapshot.json
packagr/.mypy_cache/3.7/_ast.data.json
packagr/.mypy_cache/3.7/_ast.meta.json
packagr/.mypy_cache/3.7/_importlib_modulespec.data.json
packagr/.mypy_cache/3.7/_importlib_modulespec.meta.json
packagr/.mypy_cache/3.7/abc.data.json
packagr/.mypy_cache/3.7/abc.meta.json
packagr/.mypy_cache/3.7/ast.data.json
packagr/.mypy_cache/3.7/ast.meta.json
packagr/.mypy_cache/3.7/builtins.data.json
packagr/.mypy_cache/3.7/builtins.meta.json
packagr/.mypy_cache/3.7/codecs.data.json
packagr/.mypy_cache/3.7/codecs.meta.json
packagr/.mypy_cache/3.7/collections/__init__.data.json
packagr/.mypy_cache/3.7/collections/__init__.meta.json
packagr/.mypy_cache/3.7/collections/abc.data.json
packagr/.mypy_cache/3.7/collections/abc.meta.json
packagr/.mypy_cache/3.7/datetime.data.json
packagr/.mypy_cache/3.7/datetime.meta.json
packagr/.mypy_cache/3.7/importlib/__init__.data.json
packagr/.mypy_cache/3.7/importlib/__init__.meta.json
packagr/.mypy_cache/3.7/importlib/abc.data.json
packagr/.mypy_cache/3.7/importlib/abc.meta.json
packagr/.mypy_cache/3.7/importlib/machinery.data.json
packagr/.mypy_cache/3.7/importlib/machinery.meta.json
packagr/.mypy_cache/3.7/importlib/util.data.json
packagr/.mypy_cache/3.7/importlib/util.meta.json
packagr/.mypy_cache/3.7/io.data.json
packagr/.mypy_cache/3.7/io.meta.json
packagr/.mypy_cache/3.7/mmap.data.json
packagr/.mypy_cache/3.7/mmap.meta.json
packagr/.mypy_cache/3.7/os/__init__.data.json
packagr/.mypy_cache/3.7/os/__init__.meta.json
packagr/.mypy_cache/3.7/os/path.data.json
packagr/.mypy_cache/3.7/os/path.meta.json
packagr/.mypy_cache/3.7/pathlib.data.json
packagr/.mypy_cache/3.7/pathlib.meta.json
packagr/.mypy_cache/3.7/posix.data.json
packagr/.mypy_cache/3.7/posix.meta.json
packagr/.mypy_cache/3.7/sys.data.json
packagr/.mypy_cache/3.7/sys.meta.json
packagr/.mypy_cache/3.7/time.data.json
packagr/.mypy_cache/3.7/time.meta.json
packagr/.mypy_cache/3.7/toml.data.json
packagr/.mypy_cache/3.7/toml.meta.json
packagr_cli-0.3.0.dist-info/entry_points.txt
packagr_cli-0.3.0.dist-info/WHEEL
packagr_cli-0.3.0.dist-info/METADATA
packagr_cli-0.3.0.dist-info/RECORD
