Metadata-Version: 2.1
Name: packagr-cli
Version: 0.3.0
Summary: A CLI for https://www.packagr.app
Home-page: UNKNOWN
License: UNKNOWN
Author: Chris Davies
Author-email: chris@packagr.app
Requires-Python: >=3.6.2,<4.0.0
Classifier: Programming Language :: Python :: 3
Classifier: Programming Language :: Python :: 3.7
Requires-Dist: cleo (>=0.7.2,<0.8.0)
Requires-Dist: requests (>=2.21,<3.0)
Requires-Dist: toml (>=0.10.0,<0.11.0)
Requires-Dist: wheel (>=0.33.1,<0.34.0)
